enhancement/__init__.py
enhancement/cache_result.py
enhancement/graph.py
enhancement/iterable.py
enhancement/ndict.py
enhancement/safe_get.py
enhancement/singleton.py
enhancement/timeit.py
enhancement-0.2.0.dist-info/LICENSE
enhancement-0.2.0.dist-info/METADATA
enhancement-0.2.0.dist-info/WHEEL
enhancement-0.2.0.dist-info/RECORD
