Metadata-Version: 2.3
Name: enhancement
Version: 0.2.0
Summary: A collection of Python enhancements for better development experience
License: MIT
Keywords: enhancement,utilities,development,tools
Author: Harry Zhang
Author-email: HarryZhang0415@gmail.com
Requires-Python: >=3.11,<3.12
Classifier: Development Status :: 4 - Beta
Classifier: Intended Audience :: Developers
Classifier: License :: OSI Approved :: MIT License
Classifier: Programming Language :: Python :: 3
Classifier: Programming Language :: Python :: 3.11
Classifier: Topic :: Software Development :: Libraries :: Python Modules
Requires-Dist: exchange-calendars (>=4.10,<5.0)
Requires-Dist: matplotlib (>=3.10.1,<4.0.0)
Requires-Dist: networkx (>=3.4.2,<4.0.0)
Project-URL: Documentation, https://github.com/HarryZhang0415/enhancement#readme
Project-URL: Repository, https://github.com/HarryZhang0415/enhancement
